{
    "name": "1d56a6ef-86725847",
    "frames": [
        {
            "timestamp": 10000,
            "objects": [
                {
                    "category": "car",
                    "id": 0,
                    "attributes": {
                        "occluded": true,
                        "truncated": false,
                        "trafficLightColor": "none"
                    },
                    "box2d": {
                        "x1": 466.290374,
                        "y1": 459.554238,
                        "x2": 495.230812,
                        "y2": 479.513162
                    }
                },
                {
                    "category": "car",
                    "id": 1,
                    "attributes": {
                        "occluded": false,
                        "truncated": false,
                        "trafficLightColor": "none"
                    },
                    "box2d": {
                        "x1": 257.719611,
                        "y1": 490.490571,
                        "x2": 282.668268,
                        "y2": 508.453602
                    }
                },
                {
                    "category": "car",
                    "id": 2,
                    "attributes": {
                        "occluded": true,
                        "truncated": false,
                        "trafficLightColor": "none"
                    },
                    "box2d": {
                        "x1": 320.590225,
                        "y1": 479.513162,
                        "x2": 341.547093,
                        "y2": 495.480303
                    }
                },
                {
                    "category": "car",
                    "id": 3,
                    "attributes": {
                        "occluded": true,
                        "truncated": false,
                        "trafficLightColor": "none"
                    },
                    "box2d": {
                        "x1": 311.608708,
                        "y1": 497.476196,
                        "x2": 330.56969,
                        "y2": 520.428958
                    }
                },
                {
                    "category": "car",
                    "id": 4,
                    "attributes": {
                        "occluded": false,
                        "truncated": false,
                        "trafficLightColor": "none"
                    },
                    "box2d": {
                        "x1": 318.145244,
                        "y1": 474.523432,
                        "x2": 443.337611,
                        "y2": 575.415793
                    }
                },
                {
                    "category": "car",
                    "id": 5,
                    "attributes": {
                        "occluded": false,
                        "truncated": false,
                        "trafficLightColor": "none"
                    },
                    "box2d": {
                        "x1": 540.138396,
                        "y1": 426.622012,
                        "x2": 729.748178,
                        "y2": 582.301623
                    }
                },
                {
                    "category": "traffic sign",
                    "id": 6,
                    "attributes": {
                        "occluded": false,
                        "truncated": false,
                        "trafficLightColor": "none"
                    },
                    "box2d": {
                        "x1": 621.121728,
                        "y1": 377.024102,
                        "x2": 659.043683,
                        "y2": 401.97276
                    }
                },
                {
                    "category": "traffic sign",
                    "id": 7,
                    "attributes": {
                        "occluded": false,
                        "truncated": false,
                        "trafficLightColor": "none"
                    },
                    "box2d": {
                        "x1": 722.91224,
                        "y1": 393.98919,
                        "x2": 745.865004,
                        "y2": 414.946058
                    }
                },
                {
                    "category": "traffic sign",
                    "id": 8,
                    "attributes": {
                        "occluded": true,
                        "truncated": false,
                        "trafficLightColor": "none"
                    },
                    "box2d": {
                        "x1": 616.131994,
                        "y1": 352.075448,
                        "x2": 642.078596,
                        "y2": 375.028212
                    }
                },
                {
                    "category": "traffic light",
                    "id": 9,
                    "attributes": {
                        "occluded": false,
                        "truncated": false,
                        "trafficLightColor": "green"
                    },
                    "box2d": {
                        "x1": 416.542755,
                        "y1": 330.120616,
                        "x2": 436.50168,
                        "y2": 355.069273
                    }
                },
                {
                    "category": "traffic light",
                    "id": 10,
                    "attributes": {
                        "occluded": false,
                        "truncated": false,
                        "trafficLightColor": "red"
                    },
                    "box2d": {
                        "x1": 641.679421,
                        "y1": 406.164114,
                        "x2": 662.636294,
                        "y2": 423.129201
                    }
                },
                {
                    "category": "traffic sign",
                    "id": 11,
                    "attributes": {
                        "occluded": false,
                        "truncated": false,
                        "trafficLightColor": "none"
                    },
                    "box2d": {
                        "x1": 1176.329113,
                        "y1": 342.295556,
                        "x2": 1213.253125,
                        "y2": 375.227782
                    }
                },
                {
                    "category": "car",
                    "id": 12,
                    "attributes": {
                        "occluded": false,
                        "truncated": false,
                        "trafficLightColor": "none"
                    },
                    "box2d": {
                        "x1": 139.659575,
                        "y1": 472.521136,
                        "x2": 251.986311,
                        "y2": 532.428729
                    }
                },
                {
                    "category": "area/drivable",
                    "id": 13,
                    "attributes": {},
                    "poly2d": [
                        [
                            277.31933,
                            597.374588,
                            "L"
                        ],
                        [
                            491.631683,
                            577.124603,
                            "L"
                        ],
                        [
                            621.569094,
                            720.562006,
                            "L"
                        ],
                        [
                            137.256927,
                            720.562006,
                            "L"
                        ],
                        [
                            277.31933,
                            597.374588,
                            "L"
                        ]
                    ]
                },
                {
                    "category": "area/alternative",
                    "id": 14,
                    "attributes": {},
                    "poly2d": [
                        [
                            522.006662,
                            590.624595,
                            "L"
                        ],
                        [
                            757.070164,
                            572.13663,
                            "L"
                        ],
                        [
                            1280.811618,
                            705.374516,
                            "L"
                        ],
                        [
                            1280.811618,
                            720.562006,
                            "L"
                        ],
                        [
                            636.756583,
                            720.562006,
                            "L"
                        ],
                        [
                            522.006662,
                            590.624595,
                            "L"
                        ]
                    ]
                },
                {
                    "category": "area/alternative",
                    "id": 15,
                    "attributes": {},
                    "poly2d": [
                        [
                            731.782357,
                            523.141504,
                            "L"
                        ],
                        [
                            1280.811618,
                            597.374588,
                            "L"
                        ],
                        [
                            1280.195222,
                            695.414688,
                            "L"
                        ],
                        [
                            734.943333,
                            556.331751,
                            "L"
                        ],
                        [
                            731.782357,
                            523.141504,
                            "L"
                        ]
                    ]
                },
                {
                    "category": "lane/double yellow",
                    "id": 16,
                    "attributes": {
                        "direction": "parallel",
                        "style": "solid"
                    },
                    "poly2d": [
                        [
                            243.000001,
                            597.268424,
                            "L"
                        ],
                        [
                            88.24737,
                            718.768424,
                            "L"
                        ]
                    ]
                },
                {
                    "category": "lane/double yellow",
                    "id": 17,
                    "attributes": {
                        "direction": "parallel",
                        "style": "solid"
                    },
                    "poly2d": [
                        [
                            272.415791,
                            598.547372,
                            "L"
                        ],
                        [
                            140.684211,
                            718.768424,
                            "L"
                        ]
                    ]
                },
                {
                    "category": "lane/single white",
                    "id": 18,
                    "attributes": {
                        "direction": "vertical",
                        "style": "solid"
                    },
                    "poly2d": [
                        [
                            264.742107,
                            611.336845,
                            "C"
                        ],
                        [
                            483.442108,
                            585.757898,
                            "C"
                        ],
                        [
                            708.536846,
                            567.852635,
                            "C"
                        ],
                        [
                            929.794741,
                            556.342108,
                            "L"
                        ]
                    ]
                },
                {
                    "category": "lane/single white",
                    "id": 19,
                    "attributes": {
                        "direction": "vertical",
                        "style": "solid"
                    },
                    "poly2d": [
                        [
                            259.626316,
                            619.010529,
                            "C"
                        ],
                        [
                            437.400002,
                            597.268424,
                            "C"
                        ],
                        [
                            712.373689,
                            571.689477,
                            "C"
                        ],
                        [
                            932.352636,
                            562.736845,
                            "L"
                        ]
                    ]
                },
                {
                    "category": "lane/single white",
                    "id": 20,
                    "attributes": {
                        "direction": "parallel",
                        "style": "solid"
                    },
                    "poly2d": [
                        [
                            512.857897,
                            597.268424,
                            "L"
                        ],
                        [
                            538.436846,
                            627.963161,
                            "L"
                        ]
                    ]
                },
                {
                    "category": "lane/single white",
                    "id": 21,
                    "attributes": {
                        "direction": "parallel",
                        "style": "solid"
                    },
                    "poly2d": [
                        [
                            523.089477,
                            593.431582,
                            "L"
                        ],
                        [
                            551.226319,
                            624.126319,
                            "L"
                        ]
                    ]
                },
                {
                    "category": "lane/single white",
                    "id": 22,
                    "attributes": {
                        "direction": "parallel",
                        "style": "dashed"
                    },
                    "poly2d": [
                        [
                            794.22632,
                            578.084214,
                            "L"
                        ],
                        [
                            1280.226322,
                            704.700004,
                            "L"
                        ]
                    ]
                },
                {
                    "category": "lane/single white",
                    "id": 23,
                    "attributes": {
                        "direction": "parallel",
                        "style": "dashed"
                    },
                    "poly2d": [
                        [
                            809.573688,
                            575.52632,
                            "L"
                        ],
                        [
                            1275.110533,
                            694.468425,
                            "L"
                        ]
                    ]
                },
                {
                    "category": "lane/crosswalk",
                    "id": 24,
                    "attributes": {
                        "direction": "vertical",
                        "style": "dashed"
                    },
                    "poly2d": [
                        [
                            1.278947,
                            619.010529,
                            "L"
                        ],
                        [
                            565.29474,
                            557.621056,
                            "L"
                        ]
                    ]
                },
                {
                    "category": "lane/crosswalk",
                    "id": 25,
                    "attributes": {
                        "direction": "vertical",
                        "style": "dashed"
                    },
                    "poly2d": [
                        [
                            6.394737,
                            597.268424,
                            "L"
                        ],
                        [
                            323.573686,
                            561.457898,
                            "L"
                        ]
                    ]
                },
                {
                    "category": "lane/crosswalk",
                    "id": 26,
                    "attributes": {
                        "direction": "vertical",
                        "style": "dashed"
                    },
                    "poly2d": [
                        [
                            441.236844,
                            549.947371,
                            "L"
                        ],
                        [
                            543.552634,
                            540.99474,
                            "L"
                        ]
                    ]
                },
                {
                    "category": "lane/crosswalk",
                    "id": 27,
                    "attributes": {
                        "direction": "vertical",
                        "style": "dashed"
                    },
                    "poly2d": [
                        [
                            446.352634,
                            519.252634,
                            "L"
                        ],
                        [
                            519.252634,
                            510.300004,
                            "L"
                        ]
                    ]
                },
                {
                    "category": "lane/crosswalk",
                    "id": 28,
                    "attributes": {
                        "direction": "vertical",
                        "style": "dashed"
                    },
                    "poly2d": [
                        [
                            720.047372,
                            546.110529,
                            "L"
                        ],
                        [
                            814.689479,
                            534.600003,
                            "L"
                        ]
                    ]
                },
                {
                    "category": "lane/crosswalk",
                    "id": 29,
                    "attributes": {
                        "direction": "vertical",
                        "style": "dashed"
                    },
                    "poly2d": [
                        [
                            274.973686,
                            534.600003,
                            "L"
                        ],
                        [
                            318.457897,
                            529.484214,
                            "L"
                        ]
                    ]
                }
            ]
        }
    ],
    "attributes": {
        "weather": "snowy",
        "scene": "city street",
        "timeofday": "night"
    }
}