{
    "name": "36454802-c3e12b3f",
    "frames": [
        {
            "timestamp": 10000,
            "objects": [
                {
                    "category": "traffic light",
                    "id": 0,
                    "attributes": {
                        "occluded": false,
                        "truncated": false,
                        "trafficLightColor": "red"
                    },
                    "box2d": {
                        "x1": 514.421375,
                        "y1": 82.902076,
                        "x2": 615.369846,
                        "y2": 134.860847
                    }
                },
                {
                    "category": "traffic light",
                    "id": 1,
                    "attributes": {
                        "occluded": false,
                        "truncated": false,
                        "trafficLightColor": "red"
                    },
                    "box2d": {
                        "x1": 677.720372,
                        "y1": 122.984555,
                        "x2": 748.978118,
                        "y2": 160.097965
                    }
                },
                {
                    "category": "traffic light",
                    "id": 2,
                    "attributes": {
                        "occluded": false,
                        "truncated": false,
                        "trafficLightColor": "red"
                    },
                    "box2d": {
                        "x1": 832.11215,
                        "y1": 154.159819,
                        "x2": 864.771948,
                        "y2": 215.025809
                    }
                },
                {
                    "category": "traffic light",
                    "id": 3,
                    "attributes": {
                        "occluded": false,
                        "truncated": false,
                        "trafficLightColor": "red"
                    },
                    "box2d": {
                        "x1": 827.658542,
                        "y1": 324.881497,
                        "x2": 861.80288,
                        "y2": 361.994905
                    }
                },
                {
                    "category": "traffic sign",
                    "id": 4,
                    "attributes": {
                        "occluded": false,
                        "truncated": false,
                        "trafficLightColor": "none"
                    },
                    "box2d": {
                        "x1": 199.699675,
                        "y1": 351.603152,
                        "x2": 232.359476,
                        "y2": 408.015532
                    }
                },
                {
                    "category": "traffic sign",
                    "id": 5,
                    "attributes": {
                        "occluded": false,
                        "truncated": false,
                        "trafficLightColor": "none"
                    },
                    "box2d": {
                        "x1": 523.328594,
                        "y1": 146.737138,
                        "x2": 616.854387,
                        "y2": 191.273229
                    }
                },
                {
                    "category": "traffic sign",
                    "id": 6,
                    "attributes": {
                        "occluded": false,
                        "truncated": false,
                        "trafficLightColor": "none"
                    },
                    "box2d": {
                        "x1": 1191.369939,
                        "y1": 298.159844,
                        "x2": 1265.596757,
                        "y2": 361.994906
                    }
                },
                {
                    "category": "car",
                    "id": 7,
                    "attributes": {
                        "occluded": true,
                        "truncated": false,
                        "trafficLightColor": "none"
                    },
                    "box2d": {
                        "x1": 112.112031,
                        "y1": 464.427911,
                        "x2": 260.565662,
                        "y2": 526.778436
                    }
                },
                {
                    "category": "car",
                    "id": 8,
                    "attributes": {
                        "occluded": false,
                        "truncated": false,
                        "trafficLightColor": "none"
                    },
                    "box2d": {
                        "x1": 238.297619,
                        "y1": 451.067085,
                        "x2": 422.380126,
                        "y2": 529.747508
                    }
                },
                {
                    "category": "car",
                    "id": 9,
                    "attributes": {
                        "occluded": true,
                        "truncated": false,
                        "trafficLightColor": "none"
                    },
                    "box2d": {
                        "x1": 18.586243,
                        "y1": 465.912448,
                        "x2": 129.926466,
                        "y2": 517.871219
                    }
                },
                {
                    "category": "car",
                    "id": 10,
                    "attributes": {
                        "occluded": false,
                        "truncated": true,
                        "trafficLightColor": "none"
                    },
                    "box2d": {
                        "x1": 0.771806,
                        "y1": 457.00523,
                        "x2": 42.338824,
                        "y2": 516.386682
                    }
                },
                {
                    "category": "area/drivable",
                    "id": 11,
                    "attributes": {},
                    "poly2d": [
                        [
                            0,
                            666.899767,
                            "L"
                        ],
                        [
                            0,
                            529.047714,
                            "L"
                        ],
                        [
                            456.677981,
                            536.534238,
                            "L"
                        ],
                        [
                            874.675584,
                            536.534238,
                            "L"
                        ],
                        [
                            978.749657,
                            504.899823,
                            "L"
                        ],
                        [
                            1280.195647,
                            522.808944,
                            "L"
                        ],
                        [
                            1280.195647,
                            677.530445,
                            "L"
                        ],
                        [
                            877.171092,
                            576.462368,
                            "C"
                        ],
                        [
                            481.633059,
                            587.692154,
                            "C"
                        ],
                        [
                            0,
                            666.899767,
                            "C"
                        ]
                    ]
                },
                {
                    "category": "lane/road curb",
                    "id": 12,
                    "attributes": {
                        "direction": "parallel",
                        "style": "solid"
                    },
                    "poly2d": [
                        [
                            406.164115,
                            521.925877,
                            "L"
                        ],
                        [
                            808.336444,
                            536.89507,
                            "L"
                        ],
                        [
                            1098.738796,
                            539.888909,
                            "L"
                        ],
                        [
                            1280.365009,
                            521.925877,
                            "L"
                        ]
                    ]
                },
                {
                    "category": "lane/crosswalk",
                    "id": 13,
                    "attributes": {
                        "direction": "parallel",
                        "style": "solid"
                    },
                    "poly2d": [
                        [
                            1174.582709,
                            548.870424,
                            "L"
                        ],
                        [
                            992.956496,
                            619.724607,
                            "L"
                        ]
                    ]
                },
                {
                    "category": "lane/crosswalk",
                    "id": 14,
                    "attributes": {
                        "direction": "parallel",
                        "style": "solid"
                    },
                    "poly2d": [
                        [
                            954.036593,
                            615.732822,
                            "L"
                        ],
                        [
                            1157.617623,
                            542.882747,
                            "L"
                        ]
                    ]
                },
                {
                    "category": "lane/crosswalk",
                    "id": 15,
                    "attributes": {
                        "direction": "parallel",
                        "style": "solid"
                    },
                    "poly2d": [
                        [
                            648.665047,
                            607.749253,
                            "L"
                        ],
                        [
                            804.34466,
                            571.823188,
                            "L"
                        ],
                        [
                            949.046862,
                            543.880694,
                            "L"
                        ]
                    ]
                },
                {
                    "category": "lane/crosswalk",
                    "id": 16,
                    "attributes": {
                        "direction": "parallel",
                        "style": "solid"
                    },
                    "poly2d": [
                        [
                            615.732822,
                            605.75336,
                            "L"
                        ],
                        [
                            786.381627,
                            567.831403,
                            "L"
                        ],
                        [
                            922.102313,
                            541.884801,
                            "L"
                        ]
                    ]
                }
            ]
        }
    ],
    "attributes": {
        "weather": "clear",
        "scene": "city street",
        "timeofday": "night"
    }
}