{
    "name": "49687470-29483711",
    "frames": [
        {
            "timestamp": 10000,
            "objects": [
                {
                    "category": "car",
                    "id": 0,
                    "attributes": {
                        "occluded": true,
                        "truncated": false,
                        "trafficLightColor": "none"
                    },
                    "box2d": {
                        "x1": 572.49193,
                        "y1": 277.82146,
                        "x2": 597.952655,
                        "y2": 298.78912
                    }
                },
                {
                    "category": "car",
                    "id": 1,
                    "attributes": {
                        "occluded": true,
                        "truncated": false,
                        "trafficLightColor": "none"
                    },
                    "box2d": {
                        "x1": 600.948038,
                        "y1": 277.82146,
                        "x2": 621.915696,
                        "y2": 297.291427
                    }
                },
                {
                    "category": "car",
                    "id": 2,
                    "attributes": {
                        "occluded": true,
                        "truncated": false,
                        "trafficLightColor": "none"
                    },
                    "box2d": {
                        "x1": 521.570479,
                        "y1": 277.82146,
                        "x2": 559.903282,
                        "y2": 299.039253
                    }
                },
                {
                    "category": "car",
                    "id": 3,
                    "attributes": {
                        "occluded": false,
                        "truncated": false,
                        "trafficLightColor": "none"
                    },
                    "box2d": {
                        "x1": 464.658266,
                        "y1": 290.252282,
                        "x2": 538.045064,
                        "y2": 315.263707
                    }
                },
                {
                    "category": "car",
                    "id": 4,
                    "attributes": {
                        "occluded": false,
                        "truncated": false,
                        "trafficLightColor": "none"
                    },
                    "box2d": {
                        "x1": 196.571789,
                        "y1": 292.875549,
                        "x2": 371.801502,
                        "y2": 378.166674
                    }
                },
                {
                    "category": "car",
                    "id": 5,
                    "attributes": {
                        "occluded": true,
                        "truncated": false,
                        "trafficLightColor": "none"
                    },
                    "box2d": {
                        "x1": 46.802806,
                        "y1": 285.309908,
                        "x2": 156.134162,
                        "y2": 313.766018
                    }
                },
                {
                    "category": "car",
                    "id": 6,
                    "attributes": {
                        "occluded": false,
                        "truncated": true,
                        "trafficLightColor": "none"
                    },
                    "box2d": {
                        "x1": 1.872112,
                        "y1": 283.81222,
                        "x2": 76.756602,
                        "y2": 337.729054
                    }
                },
                {
                    "category": "car",
                    "id": 7,
                    "attributes": {
                        "occluded": true,
                        "truncated": false,
                        "trafficLightColor": "none"
                    },
                    "box2d": {
                        "x1": 332.861563,
                        "y1": 274.826082,
                        "x2": 347.83846,
                        "y2": 295.793736
                    }
                },
                {
                    "category": "car",
                    "id": 8,
                    "attributes": {
                        "occluded": true,
                        "truncated": false,
                        "trafficLightColor": "none"
                    },
                    "box2d": {
                        "x1": 350.833839,
                        "y1": 268.835322,
                        "x2": 380.787636,
                        "y2": 294.296046
                    }
                },
                {
                    "category": "car",
                    "id": 9,
                    "attributes": {
                        "occluded": true,
                        "truncated": false,
                        "trafficLightColor": "none"
                    },
                    "box2d": {
                        "x1": 371.801499,
                        "y1": 271.830702,
                        "x2": 412.239124,
                        "y2": 301.784499
                    }
                },
                {
                    "category": "car",
                    "id": 10,
                    "attributes": {
                        "occluded": true,
                        "truncated": true,
                        "trafficLightColor": "none"
                    },
                    "box2d": {
                        "x1": 1156.590958,
                        "y1": 249.365352,
                        "x2": 1277.529411,
                        "y2": 403.627401
                    }
                },
                {
                    "category": "car",
                    "id": 11,
                    "attributes": {
                        "occluded": false,
                        "truncated": false,
                        "trafficLightColor": "none"
                    },
                    "box2d": {
                        "x1": 578.707344,
                        "y1": 274.07853,
                        "x2": 803.136164,
                        "y2": 457.094933
                    }
                },
                {
                    "category": "bus",
                    "id": 12,
                    "attributes": {
                        "occluded": true,
                        "truncated": false,
                        "trafficLightColor": "none"
                    },
                    "box2d": {
                        "x1": 755.434739,
                        "y1": 258.201722,
                        "x2": 852.784577,
                        "y2": 343.570043
                    }
                },
                {
                    "category": "traffic sign",
                    "id": 13,
                    "attributes": {
                        "occluded": false,
                        "truncated": false,
                        "trafficLightColor": "none"
                    },
                    "box2d": {
                        "x1": 968.084526,
                        "y1": 212.372413,
                        "x2": 1276.031719,
                        "y2": 372.453146
                    }
                },
                {
                    "category": "car",
                    "id": 14,
                    "attributes": {
                        "occluded": true,
                        "truncated": false,
                        "trafficLightColor": "none"
                    },
                    "box2d": {
                        "x1": 814.743258,
                        "y1": 297.740734,
                        "x2": 898.61389,
                        "y2": 347.164497
                    }
                },
                {
                    "category": "traffic light",
                    "id": 15,
                    "attributes": {
                        "occluded": false,
                        "truncated": false,
                        "trafficLightColor": "green"
                    },
                    "box2d": {
                        "x1": 473.869058,
                        "y1": 246.81928,
                        "x2": 486.489389,
                        "y2": 266.73714
                    }
                },
                {
                    "category": "traffic light",
                    "id": 16,
                    "attributes": {
                        "occluded": false,
                        "truncated": false,
                        "trafficLightColor": "green"
                    },
                    "box2d": {
                        "x1": 683.545633,
                        "y1": 252.810039,
                        "x2": 695.527151,
                        "y2": 264.791559
                    }
                },
                {
                    "category": "traffic sign",
                    "id": 17,
                    "attributes": {
                        "occluded": false,
                        "truncated": false,
                        "trafficLightColor": "none"
                    },
                    "box2d": {
                        "x1": 73.413893,
                        "y1": 120.398784,
                        "x2": 98.374616,
                        "y2": 151.232619
                    }
                },
                {
                    "category": "traffic sign",
                    "id": 18,
                    "attributes": {
                        "occluded": false,
                        "truncated": false,
                        "trafficLightColor": "none"
                    },
                    "box2d": {
                        "x1": 76.350449,
                        "y1": 152.700897,
                        "x2": 98.374616,
                        "y2": 173.256787
                    }
                },
                {
                    "category": "traffic sign",
                    "id": 19,
                    "attributes": {
                        "occluded": false,
                        "truncated": false,
                        "trafficLightColor": "none"
                    },
                    "box2d": {
                        "x1": 76.350449,
                        "y1": 179.129899,
                        "x2": 98.374616,
                        "y2": 211.432011
                    }
                },
                {
                    "category": "area/drivable",
                    "id": 20,
                    "attributes": {},
                    "poly2d": [
                        [
                            467.877894,
                            453.020359,
                            "L"
                        ],
                        [
                            882.162108,
                            467.907765,
                            "L"
                        ],
                        [
                            1084.298263,
                            596.426432,
                            "L"
                        ],
                        [
                            843.481733,
                            557.746057,
                            "C"
                        ],
                        [
                            612.647235,
                            549.011779,
                            "C"
                        ],
                        [
                            361.848672,
                            578.957876,
                            "C"
                        ],
                        [
                            467.877894,
                            453.020359,
                            "L"
                        ]
                    ]
                },
                {
                    "category": "area/alternative",
                    "id": 21,
                    "attributes": {},
                    "poly2d": [
                        [
                            812.287882,
                            361.848672,
                            "L"
                        ],
                        [
                            814.78339,
                            416.74985,
                            "L"
                        ],
                        [
                            1116.739868,
                            598.921941,
                            "L"
                        ],
                        [
                            1177.879816,
                            601.417449,
                            "C"
                        ],
                        [
                            1229.037732,
                            601.417449,
                            "C"
                        ],
                        [
                            1280.195648,
                            611.399481,
                            "C"
                        ],
                        [
                            1280.195648,
                            496.606109,
                            "L"
                        ],
                        [
                            812.287882,
                            361.848672,
                            "L"
                        ]
                    ]
                },
                {
                    "category": "lane/single white",
                    "id": 22,
                    "attributes": {
                        "direction": "parallel",
                        "style": "solid"
                    },
                    "poly2d": [
                        [
                            809.7854,
                            420.985415,
                            "L"
                        ],
                        [
                            1080.143006,
                            598.648984,
                            "L"
                        ]
                    ]
                },
                {
                    "category": "lane/single white",
                    "id": 23,
                    "attributes": {
                        "direction": "parallel",
                        "style": "solid"
                    },
                    "poly2d": [
                        [
                            809.7854,
                            409.39866,
                            "L"
                        ],
                        [
                            1123.91519,
                            596.07415,
                            "L"
                        ]
                    ]
                },
                {
                    "category": "lane/double yellow",
                    "id": 24,
                    "attributes": {
                        "direction": "parallel",
                        "style": "solid"
                    },
                    "poly2d": [
                        [
                            509.8172,
                            342.452967,
                            "C"
                        ],
                        [
                            481.494022,
                            455.745678,
                            "C"
                        ],
                        [
                            435.147004,
                            514.966868,
                            "C"
                        ],
                        [
                            364.339058,
                            575.475475,
                            "L"
                        ]
                    ]
                },
                {
                    "category": "lane/double yellow",
                    "id": 25,
                    "attributes": {
                        "direction": "parallel",
                        "style": "solid"
                    },
                    "poly2d": [
                        [
                            490.505942,
                            341.16555,
                            "C"
                        ],
                        [
                            458.320513,
                            428.709918,
                            "C"
                        ],
                        [
                            377.213231,
                            513.679451,
                            "C"
                        ],
                        [
                            284.519195,
                            576.762893,
                            "L"
                        ]
                    ]
                }
            ]
        }
    ],
    "attributes": {
        "weather": "snowy",
        "scene": "city street",
        "timeofday": "night"
    }
}