{
    "name": "67c58576-4ee15238",
    "frames": [
        {
            "timestamp": 10000,
            "objects": [
                {
                    "category": "traffic sign",
                    "id": 0,
                    "attributes": {
                        "occluded": false,
                        "truncated": false,
                        "trafficLightColor": "none"
                    },
                    "box2d": {
                        "x1": 811.040128,
                        "y1": 346.875624,
                        "x2": 843.481733,
                        "y2": 386.803753
                    }
                },
                {
                    "category": "traffic sign",
                    "id": 1,
                    "attributes": {
                        "occluded": false,
                        "truncated": false,
                        "trafficLightColor": "none"
                    },
                    "box2d": {
                        "x1": 691.25574,
                        "y1": 396.785786,
                        "x2": 706.228788,
                        "y2": 414.254342
                    }
                },
                {
                    "category": "traffic sign",
                    "id": 2,
                    "attributes": {
                        "occluded": false,
                        "truncated": false,
                        "trafficLightColor": "none"
                    },
                    "box2d": {
                        "x1": 661.309643,
                        "y1": 398.03354,
                        "x2": 671.291675,
                        "y2": 408.015572
                    }
                },
                {
                    "category": "car",
                    "id": 3,
                    "attributes": {
                        "occluded": false,
                        "truncated": true,
                        "trafficLightColor": "none"
                    },
                    "box2d": {
                        "x1": 1.247754,
                        "y1": 434.218407,
                        "x2": 157.217009,
                        "y2": 558.993811
                    }
                },
                {
                    "category": "car",
                    "id": 4,
                    "attributes": {
                        "occluded": true,
                        "truncated": false,
                        "trafficLightColor": "none"
                    },
                    "box2d": {
                        "x1": 140.996207,
                        "y1": 416.74985,
                        "x2": 289.478938,
                        "y2": 514.074667
                    }
                },
                {
                    "category": "car",
                    "id": 5,
                    "attributes": {
                        "occluded": true,
                        "truncated": false,
                        "trafficLightColor": "none"
                    },
                    "box2d": {
                        "x1": 361.848672,
                        "y1": 421.740866,
                        "x2": 430.475146,
                        "y2": 476.642044
                    }
                },
                {
                    "category": "car",
                    "id": 6,
                    "attributes": {
                        "occluded": true,
                        "truncated": false,
                        "trafficLightColor": "none"
                    },
                    "box2d": {
                        "x1": 437.961669,
                        "y1": 429.227391,
                        "x2": 472.898782,
                        "y2": 461.668996
                    }
                },
                {
                    "category": "car",
                    "id": 7,
                    "attributes": {
                        "occluded": true,
                        "truncated": false,
                        "trafficLightColor": "none"
                    },
                    "box2d": {
                        "x1": 472.898782,
                        "y1": 421.740866,
                        "x2": 511.579159,
                        "y2": 452.934719
                    }
                },
                {
                    "category": "car",
                    "id": 8,
                    "attributes": {
                        "occluded": false,
                        "truncated": true,
                        "trafficLightColor": "none"
                    },
                    "box2d": {
                        "x1": 852.216011,
                        "y1": 421.740866,
                        "x2": 1278.947894,
                        "y2": 638.85007
                    }
                },
                {
                    "category": "car",
                    "id": 9,
                    "attributes": {
                        "occluded": true,
                        "truncated": false,
                        "trafficLightColor": "none"
                    },
                    "box2d": {
                        "x1": 763.625474,
                        "y1": 401.776802,
                        "x2": 945.797564,
                        "y2": 541.525255
                    }
                },
                {
                    "category": "car",
                    "id": 10,
                    "attributes": {
                        "occluded": true,
                        "truncated": false,
                        "trafficLightColor": "none"
                    },
                    "box2d": {
                        "x1": 737.422639,
                        "y1": 419.245358,
                        "x2": 796.067079,
                        "y2": 506.588141
                    }
                },
                {
                    "category": "car",
                    "id": 11,
                    "attributes": {
                        "occluded": true,
                        "truncated": false,
                        "trafficLightColor": "none"
                    },
                    "box2d": {
                        "x1": 711.219804,
                        "y1": 416.74985,
                        "x2": 748.652427,
                        "y2": 495.358355
                    }
                },
                {
                    "category": "car",
                    "id": 12,
                    "attributes": {
                        "occluded": true,
                        "truncated": false,
                        "trafficLightColor": "none"
                    },
                    "box2d": {
                        "x1": 699.990018,
                        "y1": 420.493112,
                        "x2": 718.706329,
                        "y2": 469.15552
                    }
                },
                {
                    "category": "car",
                    "id": 13,
                    "attributes": {
                        "occluded": true,
                        "truncated": false,
                        "trafficLightColor": "none"
                    },
                    "box2d": {
                        "x1": 672.539429,
                        "y1": 426.731883,
                        "x2": 706.228788,
                        "y2": 466.660012
                    }
                },
                {
                    "category": "car",
                    "id": 14,
                    "attributes": {
                        "occluded": true,
                        "truncated": false,
                        "trafficLightColor": "none"
                    },
                    "box2d": {
                        "x1": 652.575364,
                        "y1": 426.731883,
                        "x2": 676.282691,
                        "y2": 456.67798
                    }
                },
                {
                    "category": "car",
                    "id": 15,
                    "attributes": {
                        "occluded": true,
                        "truncated": false,
                        "trafficLightColor": "none"
                    },
                    "box2d": {
                        "x1": 544.020763,
                        "y1": 419.245358,
                        "x2": 557.746057,
                        "y2": 436.713915
                    }
                },
                {
                    "category": "car",
                    "id": 16,
                    "attributes": {
                        "occluded": true,
                        "truncated": false,
                        "trafficLightColor": "none"
                    },
                    "box2d": {
                        "x1": 556.498303,
                        "y1": 415.502096,
                        "x2": 566.480335,
                        "y2": 430.475145
                    }
                },
                {
                    "category": "area/drivable",
                    "id": 17,
                    "attributes": {},
                    "poly2d": [
                        [
                            462.91675,
                            672.539429,
                            "L"
                        ],
                        [
                            633.859054,
                            647.584348,
                            "C"
                        ],
                        [
                            808.54462,
                            652.575365,
                            "C"
                        ],
                        [
                            968.257136,
                            666.300658,
                            "C"
                        ],
                        [
                            628.680911,
                            438.967799,
                            "L"
                        ],
                        [
                            619.274458,
                            438.967799,
                            "L"
                        ],
                        [
                            462.91675,
                            672.539429,
                            "L"
                        ]
                    ]
                },
                {
                    "category": "lane/double white",
                    "id": 18,
                    "attributes": {
                        "direction": "parallel",
                        "style": "solid"
                    },
                    "poly2d": [
                        [
                            584.79649,
                            472.028565,
                            "L"
                        ],
                        [
                            401.174382,
                            674.611649,
                            "L"
                        ]
                    ]
                },
                {
                    "category": "lane/double white",
                    "id": 19,
                    "attributes": {
                        "direction": "parallel",
                        "style": "solid"
                    },
                    "poly2d": [
                        [
                            591.782112,
                            474.024458,
                            "L"
                        ],
                        [
                            464.044995,
                            675.609595,
                            "L"
                        ]
                    ]
                },
                {
                    "category": "lane/double white",
                    "id": 20,
                    "attributes": {
                        "direction": "parallel",
                        "style": "solid"
                    },
                    "poly2d": [
                        [
                            529.909446,
                            477.018296,
                            "L"
                        ],
                        [
                            16.965086,
                            719.519229,
                            "L"
                        ]
                    ]
                },
                {
                    "category": "lane/double white",
                    "id": 21,
                    "attributes": {
                        "direction": "parallel",
                        "style": "solid"
                    },
                    "poly2d": [
                        [
                            519.929984,
                            475.022403,
                            "L"
                        ],
                        [
                            0,
                            696.566466,
                            "L"
                        ]
                    ]
                },
                {
                    "category": "lane/single white",
                    "id": 22,
                    "attributes": {
                        "direction": "parallel",
                        "style": "solid"
                    },
                    "poly2d": [
                        [
                            749.457616,
                            529.909446,
                            "L"
                        ],
                        [
                            797.359036,
                            562.841672,
                            "L"
                        ]
                    ]
                },
                {
                    "category": "lane/single white",
                    "id": 23,
                    "attributes": {
                        "direction": "parallel",
                        "style": "solid"
                    },
                    "poly2d": [
                        [
                            758.439132,
                            527.913553,
                            "L"
                        ],
                        [
                            798.356981,
                            554.858102,
                            "L"
                        ]
                    ]
                }
            ]
        }
    ],
    "attributes": {
        "weather": "rainy",
        "scene": "highway",
        "timeofday": "night"
    }
}